{
    "dataList": [
        {
      "id": 500101,
      "levelList": [
        {
          "level": 1,
          "name": "Manate",
          "coinlist": [
            {
              "coindescs": [
                {
                  "desc": "[OnSucceedAttack] Infligge 3 danni Contundenti bonus"
                }
              ]
            },
            {
              "coindescs": [
                {
                  "desc": "[OnSucceedAttack] Infligge 3 danni Contundenti bonus"
                }
              ]
            },
            {
              "coindescs": [
                {
                  "desc": "[OnSucceedAttack] Infligge 3 [Paralysis]"
                }
              ]
            }
          ]
        }
      ]
        },
        {
      "id": 500102,
      "levelList": [
        {
          "level": 1,
          "name": "Pedate",
          "coinlist": [
            {
              "coindescs": [
                {
                  "desc": "[OnSucceedAttack] Infligge 5 danni Contundenti bonus"
                }
              ]
            },
            {
              "coindescs": [
                {
                  "desc": "[OnSucceedAttack] Infligge 5 danni Contundenti bonus"
                }
              ]
            },
            {
              "coindescs": [
                {
                  "desc": "[OnSucceedAttack] Infligge 3 [Paralysis] il turno successivo"
                }
              ]
            }
          ]
        }
      ]
        },
        {
      "id": 500103,
      "levelList": [
        {
          "level": 1,
          "name": "Rivincita",
          "coinlist": [
            {},
            {
              "coindescs": [
                {
                  "desc": "[OnSucceedAttack] Infligge 5 danni ai PS"
                }
              ]
            }
          ]
        }
      ]
        },
        {
      "id": 500104,
      "levelList": [
        {
          "level": 1,
          "name": "Guardati Le Spalle!",
          "desc": "Se il bersaglio ha meno di 0 PS, Potere Moneta +3",
          "coinlist": [
            {
              "coindescs": [
                {
                  "desc": "[OnSucceedAttack] Recupera 10 PS"
                },
                {
                  "desc": "[OnSucceedAttack] Infligge 2 [Binding] e 2 [Reduction] il turno successivo"
                }
              ]
            },
            {
              "coindescs": [
                {
                  "desc": "[OnSucceedAttack] Infligge 20 danni ai PS"
                }
              ]
            }
          ]
        }
      ]
        },
        {
      "id": 500105,
      "levelList": [
        {
          "level": 1,
          "name": "Raduno",
          "desc": "[StartBattle] Evoca 2 alleati il turno successivo",
          "coinlist": [
            {}
          ]
        }
      ]
        },
        {
      "id": 500106,
      "levelList": [
        {
          "level": 1,
          "name": "Rendilo Indimenticabile",
          "desc": "",
          "coinlist": [
            {}
          ]
        }
      ]
        },
        {
      "id": 500107,
      "levelList": [
        {
          "level": 1,
          "name": "I MIEI COUPOOOOOOOOOOON!!!",
          "desc": "[DefeatDuel] Infligge -30% danni finali; i bersagli non possono essere Storditi.",
          "coinlist": [
            {
              "coindescs": [
                {
                  "desc": "[UnBrokenCoinOnSucceedAttack] Aumenta la Soglia di Stordimento del bersaglio di 30"
                },
                {
                  "desc": "[UnBrokenCoinOnSucceedAttack] Infligge 1 [Paralysis] il turno successivo"
                },
                {
                  "desc": "[OnSucceedAttack] Riduce l'[RicardoBookRaid] sul bersaglio di 5"
                }
              ]
            }
          ]
        }
      ]
        },
        {
      "id": 500108,
      "levelList": [
        {
          "level": 1,
          "name": "Sofferenza Promessa",
          "desc": "Dà priorità ai nemici con più [RicardoBookRaid]\n[WhenUse] Se il bersaglio ha <color=#ff6000><mark=#ff000040><b><u>3+ [RicardoBookRaid],</u></b></mark></color> converte tutte le Monete in [SuperCoin]",
          "coinlist": [
            {
              "coindescs": [
                {
                  "desc": "[OnSucceedAttack] Infligge 1 [Vulnerable] questo turno e il turno successivo"
                }
              ]
            },
            {
              "coindescs": [
                {
                  "desc": "[OnSucceedAttack] Infligge 1 [Vulnerable] questo turno e il turno successivo"
                }
              ]
            },
            {
              "coindescs": [
                {
                  "desc": "[OnSucceedAttack] Infligge ([RicardoBookRaid] sul bersaglio x 3) danni Contundenti bonus"
                },
                {
                  "desc": "[OnSucceedAttack] Riduce l'[RicardoBookRaid] del bersaglio di 3"
                }
              ]
            }
          ]
        }
      ]
        },
        {
      "id": 500109,
      "levelList": [
        {
          "level": 1,
          "name": "Basta Giochetti",
          "desc": "[StartBattle] Recupera 20 PS\n[EndBattle] Ottiene 5 [Enhancement] il turno successivo",
          "coinlist": [
            {}
          ]
        }
      ]
        },
        {
      "id": 500110,
      "levelList": [
        {
          "level": 1,
          "name": "VI CONDANNO A MORTE!!!",
          "desc": "[DefeatDuel] Infligge -30% danni finali; i bersagli non possono essere Storditi.",
          "coinlist": [
            {
              "coindescs": [
                {
                  "desc": "[SuperCoin]"
                },
                {
                  "desc": "[UnBrokenCoinOnSucceedAttack] Infligge danno pari al 3% dei PV Max per ogni [RicardoBookRaid] sul bersaglio"
                },
                {
                  "desc": "[OnSucceedAttack] Riduce l'[RicardoBookRaid] del bersaglio di 10"
                }
              ]
            }
          ]
        }
      ]
        },
        {
      "id": 500111,
      "levelList": [
        {
          "level": 1,
          "name": "Ah, Siete Di Famiglia",
          "desc": "[StartBattle] Tutte le Unità del Medio recuperano 10 PS",
          "coinlist": [
            {},
            {},
            {}
          ]
        }
      ]
        },
        {
      "id": 500112,
      "levelList": [
        {
          "level": 1,
          "name": "MI PRENDETE PER IL CULO?!?!",
          "desc": "[StartBattle] Perde 20 PS\n[StartBattle] Ottiene 6 [AttackUp]\n[StartBattle] Ottiene 4 [Vulnerable]",
          "coinlist": [
            {
              "coindescs": [
                {
                  "desc": "[SuperCoin]"
                }
              ]
            }
          ]
        }
      ]
        },
        {
      "id": 500113,
      "levelList": [
        {
          "level": 1,
          "name": "Giuro Vendetta",
          "desc": "[EndBattle] Ottiene 3 [AttackUp] il turno successivo\n- Se lo Slot Abilità di questo attacco <color=#ff6000><mark=#ff000040><b><u>è il bersaglio principale di un'Abilità Attacco nemica</u></b></mark></color>, ottiene 1 [AttackUp] in meno",
          "coinlist": [
            {}
          ]
        }
      ]
        },
        {
      "id": 500114,
      "levelList": [
        {
          "level": 1,
          "name": "QUESTA È UN'ESECUZIONE IMMEDIATA!!!",
          "coinlist": [
            {
              "coindescs": [
                {
                  "desc": "[OnSucceedAttack] Infligge danno pari all'1% dei PV massimi del bersaglio per ogni [RicardoBookRaid] sul bersaglio"
                }
              ]
            },
            {
              "coindescs": [
                {
                  "desc": "[OnSucceedAttack] Infligge danno pari all'1% dei PV massimi del bersaglio per ogni [RicardoBookRaid] sul bersaglio"
                }
              ]
            },
            {
              "coindescs": [
                {
                  "desc": "[OnSucceedAttack] Infligge danno pari all'1% dei PV massimi del bersaglio per ogni [RicardoBookRaid] sul bersaglio"
                }
              ]
            }
          ]
        }
      ]
        },
        {
      "id": 500115,
      "levelList": [
        {
          "level": 1,
          "name": "Fine Dei Test",
          "desc": "[WhenUse] Ottiene 3 [HitDamageUp] il turno successivo\n[WhenUse] Se il bersaglio ha <color=#ff6000><mark=#ff000040><b><u>5+ [RicardoBookRaid]</u></b></mark></color>, converte tutte le Monete in [SuperCoin]",
          "coinlist": [
            {},
            {}
          ]
        }
      ]
        },
        {
      "id": 500116,
      "levelList": [
        {
          "level": 1,
          "name": "La Pietà del Fratellone",
          "desc": "",
          "coinlist": [
            {
              "coindescs": [
                {
                  "desc": "[SuperCoin]"
                },
                {
                  "desc": "[OnSucceedAttack] <color=#ff6000><mark=#ff000040><b><u>Riduce l'[RicardoBookRaid] del bersaglio di 10</u></b></mark></color>"
                },
                {
                  "desc": "[UnBrokenCoinOnSucceedAttack] <color=#ff6000><mark=#ff000040><b><u>Stordisce il bersaglio</u></b></mark></color>"
                }
              ]
            }
          ]
        }
      ]
        },
        {
      "id": 500301,
      "levelList": [
        {
          "level": 1,
          "name": "Cogli la Chance",
          "desc": "[BeforeHit] Ottiene 5 Scudo per ogni [MiddleFingerBook] sul bersaglio (una volta per turno; max 50)\n[WhenUse] Se il bersaglio ha 5+ [MiddleFingerBook], Potere Base +3 e infligge 4 [DefenseDown]",
          "coinlist": [
            {}
          ]
        }
      ]
        },
        {
      "id": 500401,
      "levelList": [
        {
          "level": 1,
          "name": "Rappresaglia Molteplice",
          "desc": "",
          "coinlist": [
            {}
          ]
        }
      ]
        },
        {
      "id": 501203,
      "levelList": [
        {
          "level": 1,
          "name": "Bearspine Breaker",
          "desc": "[WhenUse] At 8+ [Breath], deal +40% damage on Critical Hit\n[WhenUse] Final Power +1 for every 4 [Laceration] on target (max 2)\n[WhenUse] <color=#ff6000><mark color=#ff000040><b><u>At 7+ [ChoiSwordsmanship], convert all Coins into [SuperCoin]s and deal +100% damage on Critical Hit</color></mark></b></u>\n[DefeatDuel]\n- Deal -80% damage\n- Does not hit Critically\n- Damage dealt by this Skill cannot Stagger the target",
          "coinlist": [
            {
              "coindescs": [
                {
                  "desc": "[OnSucceedAttack] Inflict 1 [SlashResistDown] this turn and next turn"
                },
                {
                  "desc": "[OnSucceedAttack] Inflict 5 [Laceration] and +3 [Laceration] Count"
                }
              ]
            }
          ]
        }
      ]
        },
        {
      "id": 501207,
      "levelList": [
        {
          "level": 1,
          "name": "Tigersplitter",
          "desc": "[WhenUse] At 8+ [Breath], deal +40% damage on Critical Hit\n[WhenUse] Final Power +1 for every 4 [Laceration] on target (max 2)\n[WhenUse] <color=#ff6000><mark color=#ff000040><b><u>At 3 or fewer [ChoiSwordsmanship], convert all Coins into [SuperCoin]s and deal +100% damage on Critical Hit</color></mark></b></u>\n[DefeatDuel]\n- Deal -80% damage\n- Does not hit Critically\n- Damage dealt by this Skill cannot Stagger the target",
          "coinlist": [
            {
              "coindescs": [
                {
                  "desc": "[OnSucceedAttack] Inflict 2 [Laceration] and +2 [Laceration] Count"
                }
              ]
            },
            {
              "coindescs": [
                {
                  "desc": "[OnSucceedAttack] Inflict 2 [Laceration] and +2 [Laceration] Count"
                }
              ]
            },
            {
              "coindescs": [
                {
                  "desc": "[OnSucceedAttack] Inflict 2 [Binding] next turn"
                }
              ]
            },
            {
              "coindescs": [
                {
                  "desc": "[OnSucceedAttack] Inflict 1 [SlashResistDown] this turn and next turn"
                }
              ]
            }
          ]
        }
      ]
        },
        {
      "id": 501209,
      "levelList": [
        {
          "level": 1,
          "name": "Sword of the Homeland [Sal] - Reassume Stance",
          "desc": "Unaffected by [ChoiSwordsmanship]\nIf target's Skill is [SupportProtect] Exclusive Skill, convert into [SuperCoin]\n[StartDuel] <color=#ff6000><mark color=#ff000040><b><u>Lose 3 [ChoiSwordsmanship]</color></mark></b></u>\n- If target's Skill is [SupportProtect] Exclusive Skill, this effect does not activate\n[EndSkill] <color=#ff6000><mark color=#ff000040><b><u>On Hit as an Unopposed Attack, or On Hit against target that used [SupportProtect] Exclusive Skill, gain 2 [ChoiSwordsmanship]</color></mark></b></u>",
          "coinlist": [
            {}
          ]
        }
      ]
        },
        {
      "id": 501210,
      "levelList": [
        {
          "level": 1,
          "name": "Sword of the Homeland [Sal] - Swordhoning",
          "desc": "Unaffected by [ChoiSwordsmanship]\nIf target's Skill is [SupportProtect] Exclusive Skill, convert into [SuperCoin]\n[StartDuel] <color=#ff6000><mark color=#ff000040><b><u>Gain 3 [ChoiSwordsmanship]</color></mark></b></u>\n- If target's Skill is [SupportProtect] Exclusive Skill, this effect does not activate\n[EndSkill] <color=#ff6000><mark color=#ff000040><b><u>On Hit as an Unopposed Attack, or On Hit against target that used [SupportProtect] Exclusive Skill, lose 2 [ChoiSwordsmanship]</color></mark></b></u>",
          "coinlist": [
            {}
          ]
        }
      ]
        },
        {
      "id": 501303,
      "levelList": [
        {
          "level": 1,
          "name": "Bearspine Breaker",
          "desc": "[WhenUse] At 8+ [Breath], deal +40% damage on Critical Hit\n[WhenUse] Final Power +1 for every 4 [Laceration] on target (max 2)\n[WhenUse] At more than 6 [ChoiSwordsmanship], gain Final Power for every excess [ChoiSwordsmanship] Stack (max 3)\n[WhenUse] <color=#ff6000><mark color=#ff000040><b><u>At 7+ [ChoiSwordsmanship], convert all Coins into [SuperCoin]s and deal +100% damage on Critical Hit</color></mark></b></u>\n[DefeatDuel]\n- Deal -80% damage\n- Does not hit Critically\n- Damage dealt by this Skill cannot Stagger the target",
          "coinlist": [
            {
              "coindescs": [
                {
                  "desc": "[OnSucceedAttack] Inflict 1 [SlashResistDown] this turn and next turn"
                },
                {
                  "desc": "[OnSucceedAttack] Inflict 5 [Laceration] and +3 [Laceration] Count"
                }
              ]
            }
          ]
        }
      ]
        },
        {
      "id": 501304,
      "levelList": [
        {
          "level": 1,
          "name": "Even Sanguns Shall Be Cleft Under This Sword",
          "desc": "Targets the enemy that has the most [Laceration]\n[WhenUse] Cannot be Staggered from taking damage until this Skill ends\n[WhenUse] Final Power +1 for every 4 [Laceration] on target (max 3)\n[WhenUse] At more than 6 [ChoiSwordsmanship], gain Final Power +2 for every excess [ChoiSwordsmanship] Stack (max 6)\n[WinDuel] <color=#ff6000><mark color=#ff000040><b><u>This Skill always flips Head, hits Critically, and does not consume [Breath] Count</color></mark></b></u>\n[BeforeAttack] Deal +30% damage on Critical Hit for every 2 [ChoiSwordsmanship] on self (max 120%)\n[DefeatDuel]\n- Deal -80% damage\n- Does not hit Critically\n- Damage dealt by this Skill cannot Stagger the target",
          "coinlist": [
            {
              "coindescs": [
                {
                  "desc": "[SuperCoin]"
                },
                {
                  "desc": "[UnBrokenCoinOnSucceedAttack] Deal (([Breath] on self x 10)% of this Coin's final damage) Slash damage (max 100%)"
                },
                {
                  "desc": "[UnBrokenCoinOnSucceedAttack] Deal (([Laceration] on target x 10)% of this Coin's final damage) Lust damage (max 100%)"
                },
                {
                  "desc": "[OnSucceedAttack] Activate [Laceration] on target once. Target loses 1 [Laceration] Count"
                }
              ]
            }
          ]
        }
      ]
        },
        {
      "id": 501307,
      "levelList": [
        {
          "level": 1,
          "name": "Tigersplitter",
          "desc": "[WhenUse] At 8+ [Breath], deal +40% damage on Critical Hit\n[WhenUse] Final Power +1 for every 4 [Laceration] on target (max 2)\n[WhenUse] <color=#ff6000><mark color=#ff000040><b><u>At 3 or fewer [ChoiSwordsmanship], convert all Coins into [SuperCoin]s and deal +100% damage on Critical Hit</color></mark></b></u>\n[DefeatDuel]\n- Deal -80% damage\n- Does not hit Critically\n- Damage dealt by this Skill cannot Stagger the target",
          "coinlist": [
            {
              "coindescs": [
                {
                  "desc": "[OnSucceedAttack] Inflict 2 [Laceration] and +2 [Laceration] Count"
                }
              ]
            },
            {
              "coindescs": [
                {
                  "desc": "[OnSucceedAttack] Inflict 2 [Laceration] and +2 [Laceration] Count"
                }
              ]
            },
            {
              "coindescs": [
                {
                  "desc": "[OnSucceedAttack] Inflict 2 [Binding] next turn"
                }
              ]
            },
            {
              "coindescs": [
                {
                  "desc": "[OnSucceedAttack] Inflict 1 [SlashResistDown] this turn and next turn"
                }
              ]
            }
          ]
        }
      ]
        },
        {
      "id": 501308,
      "levelList": [
        {
          "level": 1,
          "name": "No Tiger's Flesh Shall Be Left Uncloven",
          "desc": "Targets the enemy that has the most [Laceration]\n<color=#ff6000><mark color=#ff000040><b><u>Can Clash with this Skill regardless of Speed</color></mark></b></u>\n[WhenUse] Cannot be Staggered from taking damage until this Skill ends\n[WhenUse] Final Power +1 for every 4 [Laceration] on target (max 3)\n[WinDuel] <color=#ff6000><mark color=#ff000040><b><u>This Skill always flips Head, hits Critically, and does not consume [Breath] Count</color></mark></b></u>\n[BeforeAttack] Deal +30% damage on Critical Hit for every 2 [Breath] on self (max 120%)\n[DefeatDuel]\n- Deal -80% damage\n- Does not hit Critically\n- Damage dealt by this Skill cannot Stagger the target",
          "coinlist": [
            {
              "coindescs": [
                {
                  "desc": "[SuperCoin]"
                },
                {
                  "desc": "[OnSucceedAttack] Inflict 2 [Laceration]"
                },
                {
                  "desc": "[OnSucceedAttack] Activate [Laceration] on target once. Target loses 1 [Laceration] Count"
                }
              ]
            },
            {
              "coindescs": [
                {
                  "desc": "[SuperCoin]"
                },
                {
                  "desc": "[OnSucceedAttack] Inflict 2 [Laceration]"
                },
                {
                  "desc": "[OnSucceedAttack] Activate [Laceration] on target once. Target loses 1 [Laceration] Count"
                }
              ]
            },
            {
              "coindescs": [
                {
                  "desc": "[SuperCoin]"
                },
                {
                  "desc": "[OnSucceedAttack] Inflict 2 [Laceration]"
                },
                {
                  "desc": "[OnSucceedAttack] Activate [Laceration] on target once. Target loses 1 [Laceration] Count"
                }
              ]
            },
            {
              "coindescs": [
                {
                  "desc": "[SuperCoin]"
                },
                {
                  "desc": "[OnSucceedAttack] If the main target has 10+ [Laceration], inflict +8 [Laceration] Count on targets hit by this Coin"
                },
                {
                  "desc": "[UnBrokenCoinOnSucceedAttack] Inflict +8 [Laceration] Count"
                }
              ]
            }
          ]
        }
      ]
        },
        {
      "id": 501309,
      "levelList": [
        {
          "level": 1,
          "name": "Sword of the Homeland [Sal] - Reassume Stance",
          "desc": "Unaffected by [ChoiSwordsmanship]\nIf target's Skill is [SupportProtect] Exclusive Skill, convert into [SuperCoin]\n[StartDuel] <color=#ff6000><mark color=#ff000040><b><u>Lose 3 [ChoiSwordsmanship]</color></mark></b></u>\n- If target's Skill is [SupportProtect] Exclusive Skill, this effect does not activate\n[EndSkill] <color=#ff6000><mark color=#ff000040><b><u>On Hit as an Unopposed Attack, or On Hit against target that used [SupportProtect] Exclusive Skill, gain 2 [ChoiSwordsmanship]</color></mark></b></u>",
          "coinlist": [
            {}
          ]
        }
      ]
        },
        {
      "id": 501310,
      "levelList": [
        {
          "level": 1,
          "name": "Sword of the Homeland [Sal] - Swordhoning",
          "desc": "Unaffected by [ChoiSwordsmanship]\nIf target's Skill is [SupportProtect] Exclusive Skill, convert into [SuperCoin]\n[StartDuel] <color=#ff6000><mark color=#ff000040><b><u>Gain 3 [ChoiSwordsmanship]</color></mark></b></u>\n- If target's Skill is [SupportProtect] Exclusive Skill, this effect does not activate\n[EndSkill] <color=#ff6000><mark color=#ff000040><b><u>On Hit as an Unopposed Attack, or On Hit against target that used [SupportProtect] Exclusive Skill, lose 2 [ChoiSwordsmanship]</color></mark></b></u>",
          "coinlist": [
            {}
          ]
        }
      ]
        }
    ]
  }
  